{
  "swagger": "2.0",
  "info":{
  "description": 
    "Fast Healthcare Interoperability Resources (FHIR, pronounced \"Fire\") defines a set of \"Resources\" that represent granular clinical concepts. The resources can be managed in isolation, or aggregated into complex documents. Technically, FHIR is designed for the web; the resources are based on simple XML or JSON structures, with an http-based RESTful protocol where each resource has predictable URL. Where possible, open internet standards are used for data representation. \n",
  "version": "1.4.0",
  "title": "FHIR Medication-Dispense resource API documentation"
  },
  "host": "healthapix-demo-test.apigee.net",
  "schemes":[
     "https"
     ],
  "basePath": "/v1/dstu2",
  "produces":[
    "application/json+fhir;charset=UTF-8",
    "application/xml+fhir;charset=UTF-8"
    ],
  "definitions": {
    "MedicationDispense": {
      "description": "",
      "type": "object",
      "properties": {
        "resourceType": {
          "type": "string",
          "minLength": 1
        },
        "id": {
          "type": "string",
          "minLength": 1
        },
        "text": {
          "type": "object",
          "properties": {
            "status": {
              "type": "string",
              "minLength": 1
            },
            "div": {
              "type": "string",
              "minLength": 1
            }
          },
          "required": [
            "status",
            "div"
          ]
        },
        "status": {
          "type": "string",
          "minLength": 1
        },
        "medicationReference": {
          "type": "object",
          "properties": {
            "reference": {
              "type": "string",
              "minLength": 1
            },
            "_reference": {
              "type": "object",
              "properties": {
                "fhir_comments": {
                  "type": "array",
                  "items": {
                    "properties": {}
                  }
                }
              },
              "required": [
                "fhir_comments"
              ]
            },
            "display": {
              "type": "string",
              "minLength": 1
            }
          },
          "required": [
            "reference",
            "_reference",
            "display"
          ]
        },
        "patient": {
          "type": "object",
          "properties": {
            "reference": {
              "type": "string",
              "minLength": 1
            }
          },
          "required": [
            "reference"
          ]
        },
        "dispenser": {
          "type": "object",
          "properties": {
            "reference": {
              "type": "string",
              "minLength": 1
            }
          },
          "required": [
            "reference"
          ]
        },
        "authorizingPrescription": {
          "type": "array",
          "uniqueItems": true,
          "minItems": 1,
          "items": {
            "required": [
              "reference"
            ],
            "properties": {
              "reference": {
                "type": "string",
                "minLength": 1
              }
            }
          }
        },
        "type": {
          "type": "object",
          "properties": {
            "coding": {
              "type": "array",
              "uniqueItems": true,
              "minItems": 1,
              "items": {
                "required": [
                  "system",
                  "code",
                  "display"
                ],
                "properties": {
                  "system": {
                    "type": "string",
                    "minLength": 1
                  },
                  "code": {
                    "type": "string",
                    "minLength": 1
                  },
                  "display": {
                    "type": "string",
                    "minLength": 1
                  }
                }
              }
            }
          },
          "required": [
            "coding"
          ]
        },
        "quantity": {
          "type": "object",
          "properties": {
            "value": {
              "type": "number"
            },
            "unit": {
              "type": "string",
              "minLength": 1
            },
            "system": {
              "type": "string",
              "minLength": 1
            },
            "code": {
              "type": "string",
              "minLength": 1
            }
          },
          "required": [
            "value",
            "unit",
            "system",
            "code"
          ]
        },
        "daysSupply": {
          "type": "object",
          "properties": {
            "value": {
              "type": "number"
            },
            "unit": {
              "type": "string",
              "minLength": 1
            },
            "system": {
              "type": "string",
              "minLength": 1
            },
            "code": {
              "type": "string",
              "minLength": 1
            }
          },
          "required": [
            "value",
            "unit",
            "system",
            "code"
          ]
        },
        "whenPrepared": {
          "type": "string",
          "minLength": 1
        },
        "whenHandedOver": {
          "type": "string",
          "minLength": 1
        },
        "dosageInstruction": {
          "type": "array",
          "uniqueItems": true,
          "minItems": 1,
          "items": {
            "properties": {
              "additionalInstructions": {
                "type": "object",
                "properties": {
                  "coding": {
                    "type": "array",
                    "uniqueItems": true,
                    "minItems": 1,
                    "items": {
                      "required": [
                        "system",
                        "code",
                        "display"
                      ],
                      "properties": {
                        "system": {
                          "type": "string",
                          "minLength": 1
                        },
                        "code": {
                          "type": "string",
                          "minLength": 1
                        },
                        "display": {
                          "type": "string",
                          "minLength": 1
                        }
                      }
                    }
                  }
                },
                "required": [
                  "coding"
                ]
              },
              "timing": {
                "type": "object",
                "properties": {
                  "repeat": {
                    "type": "object",
                    "properties": {
                      "frequency": {
                        "type": "number"
                      },
                      "period": {
                        "type": "number"
                      },
                      "periodUnit": {
                        "type": "string",
                        "minLength": 1
                      }
                    },
                    "required": [
                      "frequency",
                      "period",
                      "periodUnit"
                    ]
                  }
                },
                "required": [
                  "repeat"
                ]
              },
              "siteCodeableConcept": {
                "type": "object",
                "properties": {
                  "coding": {
                    "type": "array",
                    "uniqueItems": true,
                    "minItems": 1,
                    "items": {
                      "required": [
                        "system",
                        "code",
                        "display"
                      ],
                      "properties": {
                        "system": {
                          "type": "string",
                          "minLength": 1
                        },
                        "code": {
                          "type": "string",
                          "minLength": 1
                        },
                        "display": {
                          "type": "string",
                          "minLength": 1
                        }
                      }
                    }
                  }
                },
                "required": [
                  "coding"
                ]
              },
              "route": {
                "type": "object",
                "properties": {
                  "coding": {
                    "type": "array",
                    "uniqueItems": true,
                    "minItems": 1,
                    "items": {
                      "required": [
                        "system",
                        "code",
                        "display"
                      ],
                      "properties": {
                        "system": {
                          "type": "string",
                          "minLength": 1
                        },
                        "code": {
                          "type": "string",
                          "minLength": 1
                        },
                        "display": {
                          "type": "string",
                          "minLength": 1
                        }
                      }
                    }
                  }
                },
                "required": [
                  "coding"
                ]
              },
              "doseQuantity": {
                "type": "object",
                "properties": {
                  "value": {
                    "type": "number"
                  },
                  "unit": {
                    "type": "string",
                    "minLength": 1
                  },
                  "system": {
                    "type": "string",
                    "minLength": 1
                  },
                  "code": {
                    "type": "string",
                    "minLength": 1
                  }
                },
                "required": [
                  "value",
                  "unit",
                  "system",
                  "code"
                ]
              }
            }
          }
        }
      },
      "required": [
        "resourceType",
        "id",
        "text",
        "status",
        "medicationReference",
        "patient",
        "dispenser",
        "authorizingPrescription",
        "type",
        "quantity",
        "daysSupply",
        "whenPrepared",
        "whenHandedOver",
        "dosageInstruction"
      ]
    },
    "metaBody": {
      "type": "string"
    }
  },
  "paths": {
    "/MedicationDispense": {
      "parameters": [],
      "post": {
        "tags":["MedicationDispense"],
        "consumes":[
          "application/json",
          "application/xml"
          ],
        "parameters": [
          {
            "name": "Authorization",
            "in": "header",
            "required": false,
            "description": "Specify access token for API in the given format: Bearer [access_token].",
            "type": "string"
          },
          {
            "name": "Accept",
            "description": "The Accept request-header field can be used to specify certain media types which are acceptable for the response.",
            "in": "header",
            "required": false,
            "default": "application/json+fhir;charset=UTF-8",
            "type": "string"
          },
          {
            "name": "Resource data",
            "in": "body",
            "description": "The request body should be a valid data payload.",
            "required": true,
            "schema": {
              "$ref": "#/definitions/MedicationDispense"
            }
          },
          {
            "name": "If-None-Exist",
            "in": "header",
            "required": false,
            "description": "Specify the search query for conditional create.",
            "type": "string"
          }
        ],
        "security": [
          {
            "OAuthV2B2C": [
              "patient/Medicationdispense.write"
            ]
          },
          {
            "OAuthV2B2B":[
              "patient/Medicationdispense.write"
            ]
          }
        ],
        "produces": [
          "application/json+fhir;charset=UTF-8",
          "application/xml+fhir;charset=UTF-8"
        ],
        "responses": {
          "201": {
            "description": "Successful creation"
          },
          "400": {
            "description": "MedicationDispense could not be parsed or failed basic FHIR validation rules"
          },
          "404": {
            "description": "MedicationDispense not found."
          },
          "422": {
            "description": "The MedicationDispense resource violated applicable FHIR profiles or server business rules."
          },
          "default": {
            "description": "unexpected error"
          }
        },
        "operationId": "Create MedicationDispense",
        "description": "Create a new MedicationDispense with a server assigned id.<p><a href = 'https://www.hl7.org/fhir/medicationdispense.html'>FHIR documentation for MedicationDispense.</a></p>"
      },
      "put": {
        "tags":["MedicationDispense"],
        "consumes":[
          "application/json",
          "application/xml"
          ],
        "parameters": [
          {
            "name": "Authorization",
            "in": "header",
            "required": false,
            "description": "Specify access token for API in the given format: Bearer [access_token].",
            "type": "string"
          },
          {
            "name": "Accept",
            "description": "The Accept request-header field can be used to specify certain media types which are acceptable for the response.",
            "in": "header",
            "required": false,
            "default": "application/json+fhir;charset=UTF-8",
            "type": "string"
          },
          {
            "name": "Resource data",
            "in": "body",
            "description": "The request body should be a valid data payload.",
            "required": true,
            "schema": {
              "$ref": "#/definitions/MedicationDispense"
            }
          },
          {
            "name": "_content",
            "type": "string",
            "in": "query",
            "description": "Search the contents of the resource's data using a fulltext search"
          },
          {
            "name": "_id",
            "type": "string",
            "in": "query",
            "description": "The resource identity"
          },
          {
            "name": "_language",
            "type": "string",
            "in": "query",
            "description": "The resource language"
          },
          {
            "name": "_lastUpdated",
            "type": "string",
            "in": "query",
            "description": "Only return resources which were last updated as specified by the given range. The date parameter format is yyyy-mm-ddThh:nn:ss(TZ). The prefixes >, >=, <= and < may be used on the parameter value.",
            "format": "date"
          },
          {
            "name": "_profile",
            "type": "string",
            "in": "query",
            "description": "Search for resources which have the given profile"
          },
          {
            "name": "_security",
            "type": "string",
            "in": "query",
            "description": "Search for resources which have the given security labels"
          },
          {
            "name": "_tag",
            "type": "string",
            "in": "query",
            "description": "Search for resources which have the given tag"
          },
          {
            "name": "_text",
            "type": "string",
            "in": "query",
            "description": "Search the contents of the resource's narrative using a fulltext search"
          },
          {
            "name": "code",
            "type": "string",
            "in": "query",
            "description": "Return dispenses of this medicine code"
          },
          {
            "name": "destination",
            "type": "string",
            "in": "query",
            "description": "Return dispenses that should be sent to a specific destination"
          },
          {
            "name": "dispenser",
            "type": "string",
            "in": "query",
            "description": "Return all dispenses performed by a specific individual"
          },
          {
            "name": "identifier",
            "type": "string",
            "in": "query",
            "description": "Return dispenses with this external identifier"
          },
          {
            "name": "medication",
            "type": "string",
            "in": "query",
            "description": "Return dispenses of this medicine resource"
          },
          {
            "name": "patient",
            "type": "string",
            "in": "query",
            "description": "The identity of a patient to list dispenses  for"
          },
          {
            "name": "prescription",
            "type": "string",
            "in": "query",
            "description": "The identity of a prescription to list dispenses from"
          },
          {
            "name": "receiver",
            "type": "string",
            "in": "query",
            "description": "Who collected the medication"
          },
          {
            "name": "responsibleparty",
            "type": "string",
            "in": "query",
            "description": "Return all dispenses with the specified responsible party"
          },
          {
            "name": "status",
            "type": "string",
            "in": "query",
            "description": "Status of the dispense"
          },
          {
            "name": "type",
            "type": "string",
            "in": "query",
            "description": "Return all dispenses of a specific type"
          },
          {
            "name": "whenhandedover",
            "type": "string",
            "in": "query",
            "description": "Date when medication handed over to patient (outpatient setting), or supplied to ward or clinic (inpatient setting). The date parameter format is yyyy-mm-ddThh:nn:ss(TZ). The prefixes >, >=, <= and < may be used on the parameter value.",
            "format": "date"
          },
          {
            "name": "whenprepared",
            "type": "string",
            "in": "query",
            "description": "Date when medication prepared. The date parameter format is yyyy-mm-ddThh:nn:ss(TZ). The prefixes >, >=, <= and < may be used on the parameter value.",
            "format": "date"
          }
        ],
        "security": [
          {
            "OAuthV2B2C": [
              "patient/Medicationdispense.write"
            ]
          },
          {
            "OAuthV2B2B":[
              "patient/Medicationdispense.write"
            ]
          }
        ],
        "produces": [
          "application/json+fhir;charset=UTF-8",
          "application/xml+fhir;charset=UTF-8"
        ],
        "responses": {
          "200": {
            "description": "MedicationDispense Updated."
          },
          "201": {
            "description": "MedicationDispense Created."
          },
          "400": {
            "description": "MedicationDispense could not be parsed or failed basic FHIR validation rules (or multiple matches were found)."
          },
          "403": {
            "description": "Not Authorized."
          },
          "412": {
            "description": "The given criteria is not selective enough."
          },
          "default": {
            "description": "unexpected error"
          }
        },
        "operationId": "MedicationDispense Conditional Update",
        "description": "The conditional update interaction is used to update an existing MedicationDispense based on some identification criteria, rather than by logical id.<p><a href = 'https://www.hl7.org/fhir/medicationdispense.html'>FHIR documentation for MedicationDispense.</a></p>"
      },
      "delete": {
        "tags":["MedicationDispense"],
        "parameters": [
          {
            "name": "_content",
            "type": "string",
            "in": "query",
            "description": "Search the contents of the resource's data using a fulltext search"
          },
          {
            "name": "_id",
            "type": "string",
            "in": "query",
            "description": "The resource identity"
          },
          {
            "name": "_language",
            "type": "string",
            "in": "query",
            "description": "The resource language"
          },
          {
            "name": "_lastUpdated",
            "type": "string",
            "in": "query",
            "description": "Only return resources which were last updated as specified by the given range. The date parameter format is yyyy-mm-ddThh:nn:ss(TZ). The prefixes >, >=, <= and < may be used on the parameter value.",
            "format": "date"
          },
          {
            "name": "_profile",
            "type": "string",
            "in": "query",
            "description": "Search for resources which have the given profile"
          },
          {
            "name": "_security",
            "type": "string",
            "in": "query",
            "description": "Search for resources which have the given security labels"
          },
          {
            "name": "_tag",
            "type": "string",
            "in": "query",
            "description": "Search for resources which have the given tag"
          },
          {
            "name": "_text",
            "type": "string",
            "in": "query",
            "description": "Search the contents of the resource's narrative using a fulltext search"
          },
          {
            "name": "code",
            "type": "string",
            "in": "query",
            "description": "Return dispenses of this medicine code"
          },
          {
            "name": "destination",
            "type": "string",
            "in": "query",
            "description": "Return dispenses that should be sent to a specific destination"
          },
          {
            "name": "dispenser",
            "type": "string",
            "in": "query",
            "description": "Return all dispenses performed by a specific individual"
          },
          {
            "name": "identifier",
            "type": "string",
            "in": "query",
            "description": "Return dispenses with this external identifier"
          },
          {
            "name": "medication",
            "type": "string",
            "in": "query",
            "description": "Return dispenses of this medicine resource"
          },
          {
            "name": "patient",
            "type": "string",
            "in": "query",
            "description": "The identity of a patient to list dispenses  for"
          },
          {
            "name": "prescription",
            "type": "string",
            "in": "query",
            "description": "The identity of a prescription to list dispenses from"
          },
          {
            "name": "receiver",
            "type": "string",
            "in": "query",
            "description": "Who collected the medication"
          },
          {
            "name": "responsibleparty",
            "type": "string",
            "in": "query",
            "description": "Return all dispenses with the specified responsible party"
          },
          {
            "name": "status",
            "type": "string",
            "in": "query",
            "description": "Status of the dispense"
          },
          {
            "name": "type",
            "type": "string",
            "in": "query",
            "description": "Return all dispenses of a specific type"
          },
          {
            "name": "whenhandedover",
            "type": "string",
            "in": "query",
            "description": "Date when medication handed over to patient (outpatient setting), or supplied to ward or clinic (inpatient setting). The date parameter format is yyyy-mm-ddThh:nn:ss(TZ). The prefixes >, >=, <= and < may be used on the parameter value.",
            "format": "date"
          },
          {
            "name": "whenprepared",
            "type": "string",
            "in": "query",
            "description": "Date when medication prepared. The date parameter format is yyyy-mm-ddThh:nn:ss(TZ). The prefixes >, >=, <= and < may be used on the parameter value.",
            "format": "date"
          },
          {
            "name": "Authorization",
            "in": "header",
            "required": false,
            "description": "Specify access token for API in the given format: Bearer [access_token].",
            "type": "string"
          },
          {
            "name": "Accept",
            "description": "The Accept request-header field can be used to specify certain media types which are acceptable for the response.",
            "in": "header",
            "required": false,
            "default": "application/json+fhir;charset=UTF-8",
            "type": "string"
          }
        ],
        "security": [
          {
            "OAuthV2B2C": [
              "patient/Medicationdispense.write"
            ]
          },
          {
            "OAuthV2B2B":[
              "patient/Medicationdispense.write"
            ]
          }
        ],
        "produces": [
          "application/json+fhir;charset=UTF-8",
          "application/xml+fhir;charset=UTF-8"
        ],
        "responses": {
          "200": {
            "description": "No Content."
          },
          "204": {
            "description": "No Content."
          },
          "404": {
            "description": "MedicationDispense not found."
          },
          "405": {
            "description": "Method not allowed."
          },
          "409": {
            "description": "Conflict Error."
          },
          "412": {
            "description": "The given criteria is not selective enough."
          },
          "default": {
            "description": "unexpected error"
          }
        },
        "operationId": "MedicationDispense Conditional Delete",
        "description": "The conditional delete interaction allows a client to delete MedicationDispense/MedicationDispenses  based on some selection criteria, rather than by a specific logical id.<p><a href = 'https://www.hl7.org/fhir/medicationdispense.html'>FHIR documentation for MedicationDispense.</a></p>"
      },
      "get": {
        "tags":["MedicationDispense"],
        "parameters": [
          {
            "name": "Authorization",
            "in": "header",
            "required": false,
            "description": "Specify access token for API in the given format: Bearer [access_token].",
            "type": "string"
          },
          {
            "name": "Accept",
            "description": "The Accept request-header field can be used to specify certain media types which are acceptable for the response.",
            "in": "header",
            "required": false,
            "default": "application/json+fhir;charset=UTF-8",
            "type": "string"
          },
          {
            "name": "_format",
            "in": "query",
            "description": "Format of data to be returned.",
            "type": "string",
            "x-consoleDefault": "application/json"
          },
          {
            "name": "_content",
            "type": "string",
            "in": "query",
            "description": "Search the contents of the resource's data using a fulltext search"
          },
          {
            "name": "_id",
            "type": "string",
            "in": "query",
            "description": "The resource identity"
          },
          {
            "name": "_language",
            "type": "string",
            "in": "query",
            "description": "The resource language"
          },
          {
            "name": "_lastUpdated",
            "type": "string",
            "in": "query",
            "description": "Only return resources which were last updated as specified by the given range. The date parameter format is yyyy-mm-ddThh:nn:ss(TZ). The prefixes >, >=, <= and < may be used on the parameter value.",
            "format": "date"
          },
          {
            "name": "_profile",
            "type": "string",
            "in": "query",
            "description": "Search for resources which have the given profile"
          },
          {
            "name": "_security",
            "type": "string",
            "in": "query",
            "description": "Search for resources which have the given security labels"
          },
          {
            "name": "_tag",
            "type": "string",
            "in": "query",
            "description": "Search for resources which have the given tag"
          },
          {
            "name": "_text",
            "type": "string",
            "in": "query",
            "description": "Search the contents of the resource's narrative using a fulltext search"
          },
          {
            "name": "code",
            "type": "string",
            "in": "query",
            "description": "Return dispenses of this medicine code"
          },
          {
            "name": "destination",
            "type": "string",
            "in": "query",
            "description": "Return dispenses that should be sent to a specific destination"
          },
          {
            "name": "dispenser",
            "type": "string",
            "in": "query",
            "description": "Return all dispenses performed by a specific individual"
          },
          {
            "name": "identifier",
            "type": "string",
            "in": "query",
            "description": "Return dispenses with this external identifier"
          },
          {
            "name": "medication",
            "type": "string",
            "in": "query",
            "description": "Return dispenses of this medicine resource"
          },
          {
            "name": "patient",
            "type": "string",
            "in": "query",
            "description": "The identity of a patient to list dispenses  for"
          },
          {
            "name": "prescription",
            "type": "string",
            "in": "query",
            "description": "The identity of a prescription to list dispenses from"
          },
          {
            "name": "receiver",
            "type": "string",
            "in": "query",
            "description": "Who collected the medication"
          },
          {
            "name": "responsibleparty",
            "type": "string",
            "in": "query",
            "description": "Return all dispenses with the specified responsible party"
          },
          {
            "name": "status",
            "type": "string",
            "in": "query",
            "description": "Status of the dispense"
          },
          {
            "name": "type",
            "type": "string",
            "in": "query",
            "description": "Return all dispenses of a specific type"
          },
          {
            "name": "whenhandedover",
            "type": "string",
            "in": "query",
            "description": "Date when medication handed over to patient (outpatient setting), or supplied to ward or clinic (inpatient setting). The date parameter format is yyyy-mm-ddThh:nn:ss(TZ). The prefixes >, >=, <= and < may be used on the parameter value.",
            "format": "date"
          },
          {
            "name": "whenprepared",
            "type": "string",
            "in": "query",
            "description": "Date when medication prepared. The date parameter format is yyyy-mm-ddThh:nn:ss(TZ). The prefixes >, >=, <= and < may be used on the parameter value.",
            "format": "date"
          }
        ],
        "security": [
          {
            "OAuthV2B2C": [
              "patient/Medicationdispense.read"
            ]
          },
          {
            "OAuthV2B2B":[
              "patient/Medicationdispense.read"
            ]
          }
        ],
        "produces": [
          "application/json+fhir;charset=UTF-8",
          "application/xml+fhir;charset=UTF-8"
        ],
        "responses": {
          "200": {
            "description": "MedicationDispense bundle",
            "schema": {
              "type": "array",
              "items": {
                "$ref": "#/definitions/MedicationDispense"
              }
            }
          },
          "default": {
            "description": "unexpected error"
          }
        },
        "operationId": "MedicationDispenses Search",
        "description": "Returns MedicationDispenses based on filter criteria OR Provides provision for pagination (stateid, page, page_size, _pretty & _bundletype are query parameters used for Paging).<p><a href = 'https://www.hl7.org/fhir/medicationdispense.html'>FHIR documentation for MedicationDispense.</a></p>"
      }
    },
    "/MedicationDispense/{id}": {
      "parameters": [],
      "get": {
        "tags":["MedicationDispense"],
        "parameters": [
          {
            "name": "Authorization",
            "in": "header",
            "required": false,
            "description": "Specify access token for API in the given format: Bearer [access_token].",
            "type": "string"
          },
          {
            "name": "Accept",
            "description": "The Accept request-header field can be used to specify certain media types which are acceptable for the response.",
            "in": "header",
            "required": false,
            "default": "application/json+fhir;charset=UTF-8",
            "type": "string"
          },
          {
            "name": "_format",
            "in": "query",
            "description": "Format of data to be returned.",
            "type": "string",
            "x-consoleDefault": "application/json"
          },
          {
            "name": "id",
            "description": "The logical resource id associated with the Resource.",
            "type": "string",
            "pattern": "[a-z0-9\\-\\.]{1,64}",
            "required": true,
            "in": "path"
          }
        ],
        "security": [
          {
            "OAuthV2B2C": [
              "patient/Medicationdispense.read"
            ]
          },
          {
            "OAuthV2B2B":[
              "patient/Medicationdispense.read"
            ]
          }
        ],
        "produces": [
          "application/json+fhir;charset=UTF-8",
          "application/xml+fhir;charset=UTF-8"
        ],
        "responses": {
          "200": {
            "description": "MedicationDispense Instance",
            "schema": {
              "$ref": "#/definitions/MedicationDispense"
            }
          },
          "default": {
            "description": "unexpected error"
          }
        },
        "operationId": "Read MedicationDispense",
        "description": "Returns details of MedicationDispense having id given in path.<p><a href = 'https://www.hl7.org/fhir/medicationdispense.html'>FHIR documentation for MedicationDispense.</a></p>"
      },
      "put": {
        "tags":["MedicationDispense"],
        "consumes":[
          "application/json",
          "application/xml"
          ],
        "parameters": [
          {
            "name": "Authorization",
            "in": "header",
            "required": false,
            "description": "Specify access token for API in the given format: Bearer [access_token].",
            "type": "string"
          },
          {
            "name": "Accept",
            "description": "The Accept request-header field can be used to specify certain media types which are acceptable for the response.",
            "in": "header",
            "required": false,
            "default": "application/json+fhir;charset=UTF-8",
            "type": "string"
          },
          {
            "name": "id",
            "description": "The logical resource id associated with the Resource.",
            "type": "string",
            "pattern": "[a-z0-9\\-\\.]{1,64}",
            "required": true,
            "in": "path"
          },
          {
            "name": "Resource data",
            "in": "body",
            "description": "The request body should be a valid data payload.",
            "required": true,
            "schema": {
              "$ref": "#/definitions/MedicationDispense"
            }
          }
        ],
        "security": [
          {
            "OAuthV2B2C": [
              "patient/Medicationdispense.write"
            ]
          },
          {
            "OAuthV2B2B":[
              "patient/Medicationdispense.write"
            ]
          }
        ],
        "produces": [
          "application/json+fhir;charset=UTF-8",
          "application/xml+fhir;charset=UTF-8"
        ],
        "responses": {
          "200": {
            "description": "MedicationDispense Updated."
          },
          "201": {
            "description": "MedicationDispense Created."
          },
          "400": {
            "description": "MedicationDispense could not be parsed or failed basic FHIR validation rules (or multiple matches were found)."
          },
          "403": {
            "description": "Not Authorized."
          },
          "412": {
            "description": "The given criteria is not selective enough."
          },
          "default": {
            "description": "unexpected error"
          }
        },
        "operationId": "Update MedicationDispense",
        "description": "Update an existing MedicationDispense by its id (or create it if it is new).<p><a href = 'https://www.hl7.org/fhir/medicationdispense.html'>FHIR documentation for MedicationDispense.</a></p>"
      },
      "delete": {
        "tags":["MedicationDispense"],
        "parameters": [
          {
            "name": "Authorization",
            "in": "header",
            "required": false,
            "description": "Specify access token for API in the given format: Bearer [access_token].",
            "type": "string"
          },
          {
            "name": "Accept",
            "description": "The Accept request-header field can be used to specify certain media types which are acceptable for the response.",
            "in": "header",
            "required": false,
            "default": "application/json+fhir;charset=UTF-8",
            "type": "string"
          },
          {
            "name": "id",
            "description": "The logical resource id associated with the Resource.",
            "type": "string",
            "pattern": "[a-z0-9\\-\\.]{1,64}",
            "required": true,
            "in": "path"
          }
        ],
        "security": [
          {
            "OAuthV2B2C": [
              "patient/Medicationdispense.write"
            ]
          },
          {
            "OAuthV2B2B":[
              "patient/Medicationdispense.write"
            ]
          }
        ],
        "produces": [
          "application/json+fhir;charset=UTF-8",
          "application/xml+fhir;charset=UTF-8"
        ],
        "responses": {
          "200": {
            "description": "No Content."
          },
          "204": {
            "description": "No Content."
          },
          "404": {
            "description": "MedicationDispense not found."
          },
          "405": {
            "description": "Method not allowed."
          },
          "409": {
            "description": "Conflict Error."
          },
          "412": {
            "description": "The given criteria is not selective enough."
          },
          "default": {
            "description": "unexpected error"
          }
        },
        "operationId": "Delete MedicationDispense",
        "description": "The delete interaction removes an existing MedicationDispense.<p><a href = 'https://www.hl7.org/fhir/medicationdispense.html'>FHIR documentation for MedicationDispense.</a></p>"
      }
    },
    "/MedicationDispense/{id}/_history": {
      "get": {
        "tags":["MedicationDispense"],
        "parameters": [
          {
            "name": "Authorization",
            "in": "header",
            "required": false,
            "description": "Specify access token for API in the given format: Bearer [access_token].",
            "type": "string"
          },
          {
            "name": "Accept",
            "description": "The Accept request-header field can be used to specify certain media types which are acceptable for the response.",
            "in": "header",
            "required": false,
            "default": "application/json+fhir;charset=UTF-8",
            "type": "string"
          },
          {
            "name": "_format",
            "in": "query",
            "description": "Format of data to be returned.",
            "type": "string",
            "x-consoleDefault": "application/json"
          },
          {
            "name": "_count",
            "in": "query",
            "description": "Number of records needed in response.",
            "type": "integer"
          },
          {
            "name": "_since",
            "in": "query",
            "description": "Specify an instant to only include resource versions that were created at or after the given instant in time. An instant in time is known at least to the second and always includes a time zone.",
            "type": "string",
            "pattern": "([1-9][0-9]{3}|0[0-9]{3})(-(0[1-9]|1[0-2])(-(0[1-9]|[12][0-9]|3[01])(T(([01][0-9]|2[0-3]):[0-5][0-9]:[0-5][0-9](\\.[0-9]+)?|(24:00:00(\\.0+)?))(Z|(\\+|-)((0[0-9]|1[0-3]):[0-5][0-9]|14:00))?)?)?)?"
          },
          {
            "name": "id",
            "description": "The logical resource id associated with the Resource.",
            "type": "string",
            "pattern": "[a-z0-9\\-\\.]{1,64}",
            "required": true,
            "in": "path"
          }
        ],
        "security": [
          {
            "OAuthV2B2C": [
              "patient/Medicationdispense.read"
            ]
          },
          {
            "OAuthV2B2B":[
              "patient/Medicationdispense.read"
            ]
          }
        ],
        "produces": [
          "application/json+fhir;charset=UTF-8",
          "application/xml+fhir;charset=UTF-8"
        ],
        "responses": {
          "200": {
            "description": "MedicationDispense bundle",
            "schema": {
              "type": "array",
              "items": {
                "$ref": "#/definitions/MedicationDispense"
              }
            }
          },
          "default": {
            "description": "unexpected error"
          }
        },
        "operationId": "MedicationDispense History",
        "description": "It retrieves the history of a particular MedicationDispense identified by the given id in path.<p><a href = 'https://www.hl7.org/fhir/medicationdispense.html'>FHIR documentation for MedicationDispense.</a></p>"
      }
    },
    "/MedicationDispense/_history": {
      "get": {
        "tags":["MedicationDispense"],
        "parameters": [
          {
            "name": "Authorization",
            "in": "header",
            "required": false,
            "description": "Specify access token for API in the given format: Bearer [access_token].",
            "type": "string"
          },
          {
            "name": "Accept",
            "description": "The Accept request-header field can be used to specify certain media types which are acceptable for the response.",
            "in": "header",
            "required": false,
            "default": "application/json+fhir;charset=UTF-8",
            "type": "string"
          },
          {
            "name": "_format",
            "in": "query",
            "description": "Format of data to be returned.",
            "type": "string",
            "x-consoleDefault": "application/json"
          },
          {
            "name": "_count",
            "in": "query",
            "description": "Number of records needed in response.",
            "type": "integer"
          },
          {
            "name": "_since",
            "in": "query",
            "description": "Specify an instant to only include resource versions that were created at or after the given instant in time. An instant in time is known at least to the second and always includes a time zone.",
            "type": "string",
            "pattern": "([1-9][0-9]{3}|0[0-9]{3})(-(0[1-9]|1[0-2])(-(0[1-9]|[12][0-9]|3[01])(T(([01][0-9]|2[0-3]):[0-5][0-9]:[0-5][0-9](\\.[0-9]+)?|(24:00:00(\\.0+)?))(Z|(\\+|-)((0[0-9]|1[0-3]):[0-5][0-9]|14:00))?)?)?)?"
          }
        ],
        "security": [
          {
            "OAuthV2B2C": [
              "patient/Medicationdispense.read"
            ]
          },
          {
            "OAuthV2B2B":[
              "patient/Medicationdispense.read"
            ]
          }
        ],
        "produces": [
          "application/json+fhir;charset=UTF-8",
          "application/xml+fhir;charset=UTF-8"
        ],
        "responses": {
          "200": {
            "description": "MedicationDispense bundle",
            "schema": {
              "type": "array",
              "items": {
                "$ref": "#/definitions/MedicationDispense"
              }
            }
          },
          "default": {
            "description": "unexpected error"
          }
        },
        "operationId": "MedicationDispenses History",
        "description": "It retrieves the history of all resources of MedicationDispense.<p><a href = 'https://www.hl7.org/fhir/medicationdispense.html'>FHIR documentation for MedicationDispense.</a></p>"
      }
    },
    "/MedicationDispense/{id}/_history/{vid}": {
      "get": {
        "tags":["MedicationDispense"],
        "parameters": [
          {
            "name": "vid",
            "in": "path",
            "required": true,
            "type": "string"
          },
          {
            "name": "Authorization",
            "in": "header",
            "required": false,
            "description": "Specify access token for API in the given format: Bearer [access_token].",
            "type": "string"
          },
          {
            "name": "Accept",
            "description": "The Accept request-header field can be used to specify certain media types which are acceptable for the response.",
            "in": "header",
            "required": false,
            "default": "application/json+fhir;charset=UTF-8",
            "type": "string"
          },
          {
            "name": "_format",
            "in": "query",
            "description": "Format of data to be returned.",
            "type": "string",
            "x-consoleDefault": "application/json"
          },
          {
            "name": "_count",
            "in": "query",
            "description": "Number of records needed in response.",
            "type": "integer"
          },
          {
            "name": "_since",
            "in": "query",
            "description": "Specify an instant to only include resource versions that were created at or after the given instant in time. An instant in time is known at least to the second and always includes a time zone.",
            "type": "string",
            "pattern": "([1-9][0-9]{3}|0[0-9]{3})(-(0[1-9]|1[0-2])(-(0[1-9]|[12][0-9]|3[01])(T(([01][0-9]|2[0-3]):[0-5][0-9]:[0-5][0-9](\\.[0-9]+)?|(24:00:00(\\.0+)?))(Z|(\\+|-)((0[0-9]|1[0-3]):[0-5][0-9]|14:00))?)?)?)?"
          },
          {
            "name": "id",
            "description": "The logical resource id associated with the Resource.",
            "type": "string",
            "pattern": "[a-z0-9\\-\\.]{1,64}",
            "required": true,
            "in": "path"
          }
        ],
        "security": [
          {
            "OAuthV2B2C": [
              "patient/Medicationdispense.read"
            ]
          },
          {
            "OAuthV2B2B":[
              "patient/Medicationdispense.read"
            ]
          }
        ],
        "produces": [
          "application/json+fhir;charset=UTF-8",
          "application/xml+fhir;charset=UTF-8"
        ],
        "responses": {
          "200": {
            "description": "MedicationDispense Instance",
            "schema": {
              "$ref": "#/definitions/MedicationDispense"
            }
          },
          "default": {
            "description": "unexpected error"
          }
        },
        "operationId": "MedicationDispense Version Read",
        "description": "This interaction preforms a version specific read of MedicationDispense resource.<p><a href = 'https://www.hl7.org/fhir/medicationdispense.html'>FHIR documentation for MedicationDispense.</a></p>"
      }
    },
    "/MedicationDispense/$meta": {
      "get": {
        "tags":["MedicationDispense"],
        "parameters": [
          {
            "name": "Authorization",
            "in": "header",
            "required": false,
            "description": "Specify access token for API in the given format: Bearer [access_token].",
            "type": "string"
          },
          {
            "name": "Accept",
            "description": "The Accept request-header field can be used to specify certain media types which are acceptable for the response.",
            "in": "header",
            "required": false,
            "default": "application/json+fhir;charset=UTF-8",
            "type": "string"
          },
          {
            "name": "_format",
            "in": "query",
            "description": "Format of data to be returned.",
            "type": "string",
            "x-consoleDefault": "application/json"
          }
        ],
        "security": [
          {
            "OAuthV2B2C": [
              "patient/Medicationdispense.read"
            ]
          },
          {
            "OAuthV2B2B":[
              "patient/Medicationdispense.read"
            ]
          }
        ],
        "produces": [
          "application/json+fhir;charset=UTF-8",
          "application/xml+fhir;charset=UTF-8"
        ],
        "responses": {
          "200": {
            "description": "List of all tags, profiles and security labels used for MedicationDispense"
          },
          "default": {
            "description": "unexpected error"
          }
        },
        "operationId": "MedicationDispenses Metadata",
        "description": "Retrieves a summary of the profiles, tags, and security labels for MedicationDispenses.<p><a href = 'https://www.hl7.org/fhir/medicationdispense.html'>FHIR documentation for MedicationDispense.</a></p>"
      }
    },
    "/MedicationDispense/{id}/$meta": {
      "get": {
        "tags":["MedicationDispense"],
        "parameters": [
          {
            "name": "Authorization",
            "in": "header",
            "required": false,
            "description": "Specify access token for API in the given format: Bearer [access_token].",
            "type": "string"
          },
          {
            "name": "Accept",
            "description": "The Accept request-header field can be used to specify certain media types which are acceptable for the response.",
            "in": "header",
            "required": false,
            "default": "application/json+fhir;charset=UTF-8",
            "type": "string"
          },
          {
            "name": "_format",
            "in": "query",
            "description": "Format of data to be returned.",
            "type": "string",
            "x-consoleDefault": "application/json"
          },
          {
            "name": "id",
            "description": "The logical resource id associated with the Resource.",
            "type": "string",
            "pattern": "[a-z0-9\\-\\.]{1,64}",
            "required": true,
            "in": "path"
          }
        ],
        "security": [
          {
            "OAuthV2B2C": [
              "patient/Medicationdispense.read"
            ]
          },
          {
            "OAuthV2B2B":[
              "patient/Medicationdispense.read"
            ]
          }
        ],
        "produces": [
          "application/json+fhir;charset=UTF-8",
          "application/xml+fhir;charset=UTF-8"
        ],
        "responses": {
          "200": {
            "description": "List of all tags, profiles and security labels affixed to the nominated resource."
          },
          "default": {
            "description": "unexpected error"
          }
        },
        "operationId": "MedicationDispense Metadata",
        "description": "Retrieves a summary of the profiles, tags, and security labels for given MedicationDispense resource.<p><a href = 'https://www.hl7.org/fhir/medicationdispense.html'>FHIR documentation for MedicationDispense.</a></p>"
      }
    },
    "/MedicationDispense/{id}/_history/{vid}/$meta": {
      "get": {
        "tags":["MedicationDispense"],
        "parameters": [
          {
            "name": "vid",
            "in": "path",
            "required": true,
            "type": "string"
          },
          {
            "name": "Authorization",
            "in": "header",
            "required": false,
            "description": "Specify access token for API in the given format: Bearer [access_token].",
            "type": "string"
          },
          {
            "name": "Accept",
            "description": "The Accept request-header field can be used to specify certain media types which are acceptable for the response.",
            "in": "header",
            "required": false,
            "default": "application/json+fhir;charset=UTF-8",
            "type": "string"
          },
          {
            "name": "_format",
            "in": "query",
            "description": "Format of data to be returned.",
            "type": "string",
            "x-consoleDefault": "application/json"
          },
          {
            "name": "id",
            "description": "The logical resource id associated with the Resource.",
            "type": "string",
            "pattern": "[a-z0-9\\-\\.]{1,64}",
            "required": true,
            "in": "path"
          }
        ],
        "security": [
          {
            "OAuthV2B2C": [
              "patient/Medicationdispense.read"
            ]
          },
          {
            "OAuthV2B2B":[
              "patient/Medicationdispense.read"
            ]
          }
        ],
        "produces": [
          "application/json+fhir;charset=UTF-8",
          "application/xml+fhir;charset=UTF-8"
        ],
        "responses": {
          "200": {
            "description": "List of all tags, profiles and security labels affixed to the nominated version of the resource."
          },
          "default": {
            "description": "unexpected error"
          }
        },
        "operationId": "MedicationDispense Version based Metadata",
        "description": "Retrieves a summary of the profiles, tags, and security labels for given version of the MedicationDispense.<p><a href = 'https://www.hl7.org/fhir/medicationdispense.html'>FHIR documentation for MedicationDispense.</a></p>"
      }
    },
    "/MedicationDispense/{id}/{type}": {
      "get": {
        "tags":["MedicationDispense"],
        "parameters": [
          {
            "name": "type",
            "in": "path",
             "required": true,
            "type": "string"
          },
          {
            "name": "Authorization",
            "in": "header",
            "required": false,
            "description": "Specify access token for API in the given format: Bearer [access_token].",
            "type": "string"
          },
          {
            "name": "Accept",
            "description": "The Accept request-header field can be used to specify certain media types which are acceptable for the response.",
            "in": "header",
            "required": false,
            "default": "application/json+fhir;charset=UTF-8",
            "type": "string"
          },
          {
            "name": "_format",
            "in": "query",
            "description": "Format of data to be returned.",
            "type": "string",
            "x-consoleDefault": "application/json"
          },
          {
            "name": "id",
            "description": "The logical resource id associated with the Resource.",
            "type": "string",
            "pattern": "[a-z0-9\\-\\.]{1,64}",
            "required": true,
            "in": "path"
          }
        ],
        "security": [
          {
            "OAuthV2B2C": [
              "patient/Medicationdispense.read"
            ]
          },
          {
            "OAuthV2B2B":[
              "patient/Medicationdispense.read"
            ]
          }
        ],
        "produces": [
          "application/json+fhir;charset=UTF-8",
          "application/xml+fhir;charset=UTF-8"
        ],
        "responses": {
          "200": {
            "description": "The set of resources associated with a particular MedicationDispense"
          },
          "default": {
            "description": "unexpected error"
          }
        },
        "operationId": " Compartment Search",
        "description": "Search the specified resource type in MedicationDispense compartment.<p><a href = 'https://www.hl7.org/fhir/medicationdispense.html'>FHIR documentation for MedicationDispense.</a></p>"
      }
    },
    "/MedicationDispense/_search": {
      "post": {
        "tags":["MedicationDispense"],
        "consumes":[
          "application/x-www-form-urlencoded" 
          ],
        "parameters": [
          {
            "name": "_content",
            "type": "string",
            "in": "query",
            "description": "Search the contents of the resource's data using a fulltext search"
          },
          {
            "name": "_id",
            "type": "string",
            "in": "query",
            "description": "The resource identity"
          },
          {
            "name": "_language",
            "type": "string",
            "in": "query",
            "description": "The resource language"
          },
          {
            "name": "_lastUpdated",
            "type": "string",
            "in": "query",
            "description": "Only return resources which were last updated as specified by the given range. The date parameter format is yyyy-mm-ddThh:nn:ss(TZ). The prefixes >, >=, <= and < may be used on the parameter value.",
            "format": "date"
          },
          {
            "name": "_profile",
            "type": "string",
            "in": "query",
            "description": "Search for resources which have the given profile"
          },
          {
            "name": "_security",
            "type": "string",
            "in": "query",
            "description": "Search for resources which have the given security labels"
          },
          {
            "name": "_tag",
            "type": "string",
            "in": "query",
            "description": "Search for resources which have the given tag"
          },
          {
            "name": "_text",
            "type": "string",
            "in": "query",
            "description": "Search the contents of the resource's narrative using a fulltext search"
          },
          {
            "name": "code",
            "type": "string",
            "in": "query",
            "description": "Return dispenses of this medicine code"
          },
          {
            "name": "destination",
            "type": "string",
            "in": "query",
            "description": "Return dispenses that should be sent to a specific destination"
          },
          {
            "name": "dispenser",
            "type": "string",
            "in": "query",
            "description": "Return all dispenses performed by a specific individual"
          },
          {
            "name": "identifier",
            "type": "string",
            "in": "query",
            "description": "Return dispenses with this external identifier"
          },
          {
            "name": "medication",
            "type": "string",
            "in": "query",
            "description": "Return dispenses of this medicine resource"
          },
          {
            "name": "patient",
            "type": "string",
            "in": "query",
            "description": "The identity of a patient to list dispenses  for"
          },
          {
            "name": "prescription",
            "type": "string",
            "in": "query",
            "description": "The identity of a prescription to list dispenses from"
          },
          {
            "name": "receiver",
            "type": "string",
            "in": "query",
            "description": "Who collected the medication"
          },
          {
            "name": "responsibleparty",
            "type": "string",
            "in": "query",
            "description": "Return all dispenses with the specified responsible party"
          },
          {
            "name": "status",
            "type": "string",
            "in": "query",
            "description": "Status of the dispense"
          },
          {
            "name": "type",
            "type": "string",
            "in": "query",
            "description": "Return all dispenses of a specific type"
          },
          {
            "name": "whenhandedover",
            "type": "string",
            "in": "query",
            "description": "Date when medication handed over to patient (outpatient setting), or supplied to ward or clinic (inpatient setting). The date parameter format is yyyy-mm-ddThh:nn:ss(TZ). The prefixes >, >=, <= and < may be used on the parameter value.",
            "format": "date"
          },
          {
            "name": "whenprepared",
            "type": "string",
            "in": "query",
            "description": "Date when medication prepared. The date parameter format is yyyy-mm-ddThh:nn:ss(TZ). The prefixes >, >=, <= and < may be used on the parameter value.",
            "format": "date"
          },
          {
            "name": "_content",
            "type": "string",
            "in": "formData",
            "description": "Search the contents of the resource's data using a fulltext search"
          },
          {
            "name": "_id",
            "type": "string",
            "in": "formData",
            "description": "The resource identity"
          },
          {
            "name": "_language",
            "type": "string",
            "in": "formData",
            "description": "The resource language"
          },
          {
            "name": "_lastUpdated",
            "type": "string",
            "in": "formData",
            "description": "Only return resources which were last updated as specified by the given range. The date parameter format is yyyy-mm-ddThh:nn:ss(TZ). The prefixes >, >=, <= and < may be used on the parameter value.",
            "format": "date"
          },
          {
            "name": "_profile",
            "type": "string",
            "in": "formData",
            "description": "Search for resources which have the given profile"
          },
          {
            "name": "_security",
            "type": "string",
            "in": "formData",
            "description": "Search for resources which have the given security labels"
          },
          {
            "name": "_tag",
            "type": "string",
            "in": "formData",
            "description": "Search for resources which have the given tag"
          },
          {
            "name": "_text",
            "type": "string",
            "in": "formData",
            "description": "Search the contents of the resource's narrative using a fulltext search"
          },
          {
            "name": "code",
            "type": "string",
            "in": "formData",
            "description": "Return dispenses of this medicine code"
          },
          {
            "name": "destination",
            "type": "string",
            "in": "formData",
            "description": "Return dispenses that should be sent to a specific destination"
          },
          {
            "name": "dispenser",
            "type": "string",
            "in": "formData",
            "description": "Return all dispenses performed by a specific individual"
          },
          {
            "name": "identifier",
            "type": "string",
            "in": "formData",
            "description": "Return dispenses with this external identifier"
          },
          {
            "name": "medication",
            "type": "string",
            "in": "formData",
            "description": "Return dispenses of this medicine resource"
          },
          {
            "name": "patient",
            "type": "string",
            "in": "formData",
            "description": "The identity of a patient to list dispenses  for"
          },
          {
            "name": "prescription",
            "type": "string",
            "in": "formData",
            "description": "The identity of a prescription to list dispenses from"
          },
          {
            "name": "receiver",
            "type": "string",
            "in": "formData",
            "description": "Who collected the medication"
          },
          {
            "name": "responsibleparty",
            "type": "string",
            "in": "formData",
            "description": "Return all dispenses with the specified responsible party"
          },
          {
            "name": "status",
            "type": "string",
            "in": "formData",
            "description": "Status of the dispense"
          },
          {
            "name": "type",
            "type": "string",
            "in": "formData",
            "description": "Return all dispenses of a specific type"
          },
          {
            "name": "whenhandedover",
            "type": "string",
            "in": "formData",
            "description": "Date when medication handed over to patient (outpatient setting), or supplied to ward or clinic (inpatient setting). The date parameter format is yyyy-mm-ddThh:nn:ss(TZ). The prefixes >, >=, <= and < may be used on the parameter value.",
            "format": "date"
          },
          {
            "name": "whenprepared",
            "type": "string",
            "in": "formData",
            "description": "Date when medication prepared. The date parameter format is yyyy-mm-ddThh:nn:ss(TZ). The prefixes >, >=, <= and < may be used on the parameter value.",
            "format": "date"
          },
          {
            "name": "Authorization",
            "in": "header",
            "required": false,
            "description": "Specify access token for API in the given format: Bearer [access_token].",
            "type": "string"
          },
          {
            "name": "Accept",
            "description": "The Accept request-header field can be used to specify certain media types which are acceptable for the response.",
            "in": "header",
            "required": false,
            "default": "application/json+fhir;charset=UTF-8",
            "type": "string"
          }
        ],
        "security": [
          {
            "OAuthV2B2C": [
              "patient/Medicationdispense.read"
            ]
          },
          {
            "OAuthV2B2B":[
              "patient/Medicationdispense.read"
            ]
          }
        ],
        "produces": [
          "application/json+fhir;charset=UTF-8",
          "application/xml+fhir;charset=UTF-8"
        ],
        "responses": {
          "200": {
            "description": "MedicationDispense bundle",
            "schema": {
              "type": "array",
              "items": {
                "$ref": "#/definitions/MedicationDispense"
              }
            }
          },
          "default": {
            "description": "unexpected error"
          }
        },
        "operationId": "MedicationDispenses Search using POST",
        "description": "This interaction searches a set of MedicationDispenses based on some filter criteria. Search interactions take a series of parameters of name'='value pairs encoded as an application/x-www-form-urlencoded submission for a POST.<p><a href = 'https://www.hl7.org/fhir/medicationdispense.html'>FHIR documentation for MedicationDispense.</a></p>"
      }
    },
    "/MedicationDispense/{id}/$meta-add": {
      "post": {
        "tags":["MedicationDispense"],
        "consumes":[
          "application/json",
          "application/xml"
          ],
        "parameters": [
          {
            "name": "Resource data",
            "in": "body",
            "description": "The request body should be a valid meta payload.",
            "required": true,
            "schema": {
              "$ref": "#/definitions/metaBody"
            }
          },
          {
            "name": "Authorization",
            "in": "header",
            "required": false,
            "description": "Specify access token for API in the given format: Bearer [access_token].",
            "type": "string"
          },
          {
            "name": "Accept",
            "description": "The Accept request-header field can be used to specify certain media types which are acceptable for the response.",
            "in": "header",
            "required": false,
            "default": "application/json+fhir;charset=UTF-8",
            "type": "string"
          },
          {
            "name": "id",
            "description": "The logical resource id associated with the Resource.",
            "type": "string",
            "pattern": "[a-z0-9\\-\\.]{1,64}",
            "required": true,
            "in": "path"
          }
        ],
        "security": [
          {
            "OAuthV2B2C": [
              "patient/Medicationdispense.write"
            ]
          },
          {
            "OAuthV2B2B":[
              "patient/Medicationdispense.write"
            ]
          }
        ],
        "produces": [
          "application/json+fhir;charset=UTF-8",
          "application/xml+fhir;charset=UTF-8"
        ],
        "responses": {
          "201": {
            "description": "Successful creation"
          },
          "400": {
            "description": "MedicationDispense could not be parsed or failed basic FHIR validation rules"
          },
          "404": {
            "description": "MedicationDispense not found."
          },
          "422": {
            "description": "The MedicationDispense resource violated applicable FHIR profiles or server business rules."
          },
          "default": {
            "description": "unexpected error"
          }
        },
        "operationId": "Add MedicationDispense metadata",
        "description": "Add a metadata info MedicationDispense with specified id.<p><a href = 'https://www.hl7.org/fhir/medicationdispense.html'>FHIR documentation for MedicationDispense.</a></p>"
      }
    },
    "/MedicationDispense/{id}/_history/{vid}/$meta-add": {
      "post": {
        "tags":["MedicationDispense"],
        "consumes":[
          "application/json",
          "application/xml"
          ],
        "parameters": [
          {
            "name": "vid",
            "in": "path",
            "required": true,
            "type": "string"
          },
          {
            "name": "Resource data",
            "in": "body",
            "description": "The request body should be a valid meta payload.",
            "required": true,
            "schema": {
              "$ref": "#/definitions/metaBody"
            }
          },
          {
            "name": "Authorization",
            "in": "header",
            "required": false,
            "description": "Specify access token for API in the given format: Bearer [access_token].",
            "type": "string"
          },
          {
            "name": "Accept",
            "description": "The Accept request-header field can be used to specify certain media types which are acceptable for the response.",
            "in": "header",
            "required": false,
            "default": "application/json+fhir;charset=UTF-8",
            "type": "string"
          },
          {
            "name": "id",
            "description": "The logical resource id associated with the Resource.",
            "type": "string",
            "pattern": "[a-z0-9\\-\\.]{1,64}",
            "required": true,
            "in": "path"
          }
        ],
        "security": [
          {
            "OAuthV2B2C": [
              "patient/Medicationdispense.write"
            ]
          },
          {
            "OAuthV2B2B":[
              "patient/Medicationdispense.write"
            ]
          }
        ],
        "produces": [
          "application/json+fhir;charset=UTF-8",
          "application/xml+fhir;charset=UTF-8"
        ],
        "responses": {
          "201": {
            "description": "Successful creation"
          },
          "400": {
            "description": "MedicationDispense could not be parsed or failed basic FHIR validation rules"
          },
          "404": {
            "description": "MedicationDispense not found."
          },
          "422": {
            "description": "The MedicationDispense resource violated applicable FHIR profiles or server business rules."
          },
          "default": {
            "description": "unexpected error"
          }
        },
        "operationId": "Add MedicationDispense Version based Metadata",
        "description": "Add metadata info to specified MedicationDispense resource.<p><a href = 'https://www.hl7.org/fhir/medicationdispense.html'>FHIR documentation for MedicationDispense.</a></p>"
      }
    }
  },
   "securityDefinitions": {
    "OAuthV2B2C": {
      "type": "oauth2",
      "description": "Security scheme for B2C flow using authorization code flow.",
      "scopes": {
        "patient/Medicationdispense.read": "Read permissions for Medicationdispense demographics.",
        "patient/Medicationdispense.write": "Write permissions for Medicationdispense demographics."
      },
      "flow": "accessCode",
      "authorizationUrl": "https://healthapix-demo-test.apigee.net/oauth/v2/authorize",
      "tokenUrl": "https://healthapix-demo-test.apigee.net/oauth/v2/accesstoken"
    },
    "OAuthV2B2B": {
      "type": "oauth2",
      "description": "Security scheme for B2B flow using authorization code flow.",
      "flow": "application",
      "tokenUrl": "https://healthapix-demo-test.apigee.net/oauth/v2/accesstoken?grant_type=client_credentials",
      "scopes": {
        "patient/Medicationdispense.read": "Read permissions for Medicationdispense demographics.",
        "patient/Medicationdispense.write": "Write permissions for Medicationdispense demographics."
      }
    }  
  }
}
